{
    "packages": {
        "horde/dummy": [
            {
                "name": "horde/dummy",
                "version": "v1.0.0.70400",
                "version_normalized": "1.0.0.70400",
                "source": {
                    "type": "git",
                    "url": "https://github.com/maintaina-com/dummy.git",
                    "reference": "821ded2ef45a2a6ba67bf05eeab1e97d1dd2d392"
                },
                "dist": {
                    "type": "zip",
                    "url": "https://api.github.com/repos/maintaina-com/dummy/zipball/821ded2ef45a2a6ba67bf05eeab1e97d1dd2d392",
                    "reference": "821ded2ef45a2a6ba67bf05eeab1e97d1dd2d392",
                    "shasum": ""
                },
                "require": {
                    "php": "^7.4"
                },
                "time": "2022-09-08T10:58:46+00:00",
                "type": "library",
                "license": [
                    "MIT"
                ],
                "authors": [
                    {
                        "name": "Ralf Lang",
                        "email": "ralf.lang@ralf-lang.de"
                    }
                ],
                "description": "Mock package to try out various composer, satis and versioning things",
                "support": {
                    "source": "https://github.com/maintaina-com/dummy/tree/v1.0.0.70400",
                    "issues": "https://github.com/maintaina-com/dummy/issues"
                }
            },
            {
                "name": "horde/dummy",
                "version": "v1.0.0.80100",
                "version_normalized": "1.0.0.80100",
                "source": {
                    "type": "git",
                    "url": "https://github.com/maintaina-com/dummy.git",
                    "reference": "271afd13dd8505bf737dfcd19fc9d92c30c97540"
                },
                "dist": {
                    "type": "zip",
                    "url": "https://api.github.com/repos/maintaina-com/dummy/zipball/271afd13dd8505bf737dfcd19fc9d92c30c97540",
                    "reference": "271afd13dd8505bf737dfcd19fc9d92c30c97540",
                    "shasum": ""
                },
                "require": {
                    "php": "^8.1"
                },
                "time": "2022-09-08T10:58:46+00:00",
                "type": "library",
                "license": [
                    "MIT"
                ],
                "authors": [
                    {
                        "name": "Ralf Lang",
                        "email": "ralf.lang@ralf-lang.de"
                    }
                ],
                "description": "Mock package to try out various composer, satis and versioning things",
                "support": {
                    "source": "https://github.com/maintaina-com/dummy/tree/v1.0.0.80100",
                    "issues": "https://github.com/maintaina-com/dummy/issues"
                }
            }
        ]
    }
}
